LocalDB/__init__.py
RouteDB/__init__.py
RouteDB-0.0.3.dist-info/LICENSE
RouteDB-0.0.3.dist-info/METADATA
RouteDB-0.0.3.dist-info/WHEEL
RouteDB-0.0.3.dist-info/top_level.txt
RouteDB-0.0.3.dist-info/RECORD
