Metadata-Version: 2.1
Name: RouteDB
Version: 0.0.3
Summary: A package which helps you manage local databases
Home-page: https://github.com/itsoutchy-projects/RouteDB
Author: itsoutchy
Author-email: itsoutchy@itsoutchy.xyz
License: MIT
Requires-Python: >=3.8
License-File: LICENSE
